ppmd/__init__.py
ppmd/main.py
ppmd/models/__init__.py
ppmd/models/metadata.py
ppmd/models/presentation.py
ppmd/models/slide.py
ppmd-0.1.1.dist-info/DESCRIPTION.rst
ppmd-0.1.1.dist-info/METADATA
ppmd-0.1.1.dist-info/RECORD
ppmd-0.1.1.dist-info/WHEEL
ppmd-0.1.1.dist-info/entry_points.txt
ppmd-0.1.1.dist-info/metadata.json
ppmd-0.1.1.dist-info/top_level.txt
