Metadata-Version: 2.0
Name: ppmd
Version: 0.1.1
Summary: A tool to convert from PowerPoint OOXML files to Markdown Presentations
Home-page: https://github.com/nathancastle/ppmd
Author: Nathan C. Castle
Author-email: nathan.castle@outlook.com
License: MIT
Keywords: powerpoint markdown ooxml converter document
Platform: UNKNOWN
Classifier: Development Status :: 4 - Beta
Classifier: Intended Audience :: Developers
Classifier: Topic :: Documentation
Classifier: License :: OSI Approved :: MIT License
Classifier: Programming Language :: Python :: 3
Requires-Dist: click
